scraper/__init__.py
scraper/cli.py
scraper/dir_reader.py
scraper/directories.py
scraper/main.py
scraper/data_parsing/__init__.py
scraper/data_parsing/parser.py
scraper/db/__init__.py
scraper/db/db.py
scraper/db/domains.py
scraper/db/pool.py
scraper/db/utils.py
scraper/db/models/__init__.py
scraper/db/models/base.py
scraper/db/models/domains_model.py
scraper/db/models/links_model.py
scraper/migrations/0001_init_links_table.py
scraper/migrations/0002_init_domains_table.py
tests/__init__.py
tests/conftest.py
tests/db/__init__.py
tests/db/test_domains.py
tests/db/models/__init__.py
tests/db/models/test_domains_model.py
tests/db/models/test_links_model.py
tests/dir_reader/__init__.py
tests/dir_reader/test_dir_reader.py
tests/parser/__init__.py
tests/parser/test_parser.py
scraper_twnty-0.0.1.dist-info/LICENSE
scraper_twnty-0.0.1.dist-info/METADATA
scraper_twnty-0.0.1.dist-info/WHEEL
scraper_twnty-0.0.1.dist-info/entry_points.txt
scraper_twnty-0.0.1.dist-info/top_level.txt
scraper_twnty-0.0.1.dist-info/zip-safe
scraper_twnty-0.0.1.dist-info/RECORD
